dlzoom/__init__.py
dlzoom/audio_extractor.py
dlzoom/cli.py
dlzoom/config.py
dlzoom/downloader.py
dlzoom/exceptions.py
dlzoom/handlers.py
dlzoom/logger.py
dlzoom/login.py
dlzoom/logout.py
dlzoom/output.py
dlzoom/recorder_selector.py
dlzoom/stj_minimizer.py
dlzoom/templates.py
dlzoom/token_store.py
dlzoom/whoami.py
dlzoom/zoom_client.py
dlzoom/zoom_user_client.py
dlzoom-0.3.1.dist-info/licenses/LICENSE
dlzoom-0.3.1.dist-info/METADATA
dlzoom-0.3.1.dist-info/WHEEL
dlzoom-0.3.1.dist-info/entry_points.txt
dlzoom-0.3.1.dist-info/top_level.txt
dlzoom-0.3.1.dist-info/RECORD
