Metadata-Version: 2.4
Name: dlzoom
Version: 0.3.1
Summary: CLI tool to download Zoom cloud recordings and extract audio for transcription
Author-email: Yaniv Golan <yaniv@golan.name>
Maintainer-email: Yaniv Golan <yaniv@golan.name>
License: MIT
Project-URL: Homepage, https://github.com/yaniv-golan/dlzoom
Project-URL: Repository, https://github.com/yaniv-golan/dlzoom
Project-URL: Issues, https://github.com/yaniv-golan/dlzoom/issues
Keywords: zoom,recording,download,audio,transcription,api,cli
Classifier: Development Status :: 4 - Beta
Classifier: Intended Audience :: Developers
Classifier: Intended Audience :: End Users/Desktop
Classifier: Topic :: Multimedia :: Sound/Audio :: Capture/Recording
Classifier: Topic :: Utilities
Classifier: License :: OSI Approved :: MIT License
Classifier: Programming Language :: Python :: 3
Classifier: Programming Language :: Python :: 3.11
Classifier: Programming Language :: Python :: 3.12
Classifier: Environment :: Console
Classifier: Operating System :: OS Independent
Requires-Python: >=3.11
License-File: LICENSE
Requires-Dist: requests>=2.31.0
Requires-Dist: rich-click>=1.7.0
Requires-Dist: python-dotenv>=1.0.0
Requires-Dist: rich>=13.7.0
Requires-Dist: platformdirs>=4.2.0
Provides-Extra: dev
Requires-Dist: pytest<10.0.0,>=7.4.0; extra == "dev"
Requires-Dist: pytest-cov<8.0.0,>=4.1.0; extra == "dev"
Requires-Dist: pytest-mock<4.0.0,>=3.12.0; extra == "dev"
Requires-Dist: responses<1.0.0,>=0.24.0; extra == "dev"
Requires-Dist: black<26.0.0,>=24.3.0; extra == "dev"
Requires-Dist: ruff<0.7.0,>=0.6.0; extra == "dev"
Requires-Dist: mypy<2.0.0,>=1.9.0; extra == "dev"
Requires-Dist: types-requests<3.0.0,>=2.31.0; extra == "dev"
Requires-Dist: types-PyYAML<7.0.0,>=6.0.0; extra == "dev"
Requires-Dist: ipython<10.0.0,>=8.18.0; extra == "dev"
Requires-Dist: pre-commit<5.0.0,>=3.6.0; extra == "dev"
Dynamic: license-file
